Workbook

Sheet Kertas Kerja Cash Flow
A1: PT BUKIT JAYA SEMESTA
A2: KERTAS KERJA LAPORAN ARUS KAS (STATEMENT OF CASH FLOWS)
A3: Untuk Periode yang Berakhir pada 31 Desember 2024
A4: (Saling Terhubung dengan Laporan Posisi Keuangan & Laba Rugi)
A6: No | B6: Keterangan / Pos-Pos Arus Kas | C6: Jumlah (Rp) | D6: Sumber Link / Referensi Formula | G6: Jumlah (IDR) | H6: Keterangan
A7: A | B7: ARUS KAS DARI AKTIVITAS OPERASI | H7: 1. ARUS KAS DARI AKTIVITAS OPERASI
B8: Laba Bersih Tahun Berjalan | C8: ='Laba Rugi (Income Statement)'!B26 | D8: Laba Rugi - Net Income 2024 | G8: ='Laba Rugi (Income Statement)'!B20 | H8: Laba Sebelum Pajak (Income Before Tax)
B9: Penyesuaian untuk Merekonsiliasi Laba Bersih: | H9: Penyesuaian untuk:
B10: Beban Penyusutan Aset Tetap | C10: ='Neraca (Balance Sheet)'!D23 | D10: Neraca - Selisih Akumulasi Penyusutan | G10: =C10 | H10: • Penyusutan Aset Tetap
B11: Penghasilan Komprehensif Lain (non-kas) | C11: ='Laba Rugi (Income Statement)'!B32 | D11: Laba Rugi - Total OCI | G11: =-'Laba Rugi (Income Statement)'!B17 | H11: • Beban Keuangan (Finance Expense)
B12: Penyesuaian Saldo Laba (selisih Neraca vs Laba Rugi) | C12: =-'Neraca (Balance Sheet)'!D66-'Laba Rugi (Income Statement)'!B45 | D12: Neraca Saldo Laba - Laba Komprehensif Mayoritas | G12: =-'Laba Rugi (Income Statement)'!B16 | H12: • Pendapatan Bunga / Keuangan
B13: (Kenaikan) Penurunan Aset Pajak Tangguhan | C13: ='Neraca (Balance Sheet)'!D30 | D13: Neraca - Selisih Aset Pajak Tangguhan | G13: =C11+C12 | H13: • Penghasilan Komprehensif Lain & Penyesuaian Saldo Laba
B14: Perubahan dalam Aset dan Liabilitas Operasi: | H14: Perubahan Modal Kerja:
B15: (Kenaikan) Penurunan Restricted Cash | C15: ='Neraca (Balance Sheet)'!D9 | D15: Neraca - Selisih Restricted Cash | G15: =C15 | H15: • (Kenaikan) Penurunan Restricted Cash
B16: (Kenaikan) Penurunan Piutang Usaha - Bersih | C16: ='Neraca (Balance Sheet)'!D10 | D16: Neraca - Selisih Piutang Usaha - Bersih | G16: =C16 | H16: • (Kenaikan) Penurunan Piutang Usaha - Bersih
B17: (Kenaikan) Penurunan Piutang Lain-lain - Pihak Ketiga | C17: ='Neraca (Balance Sheet)'!D11 | D17: Neraca - Selisih Piutang Lain-lain - Pihak Ketiga | G17: =C17 | H17: • (Kenaikan) Penurunan Piutang Lain-lain - Pihak Ketiga
B18: (Kenaikan) Penurunan Piutang Lain-lain - Pihak Berelasi | C18: ='Neraca (Balance Sheet)'!D12 | D18: Neraca - Selisih Piutang Lain-lain - Pihak Berelasi | G18: =C18 | H18: • (Kenaikan) Penurunan Piutang Lain-lain - Pihak Berelasi
B19: (Kenaikan) Penurunan Pajak Dibayar di Muka | C19: ='Neraca (Balance Sheet)'!D13 | D19: Neraca - Selisih Pajak Dibayar di Muka | G19: =C19 | H19: • (Kenaikan) Penurunan Pajak Dibayar di Muka
B20: (Kenaikan) Penurunan Uang Muka | C20: ='Neraca (Balance Sheet)'!D14 | D20: Neraca - Selisih Uang Muka | G20: =C20 | H20: • (Kenaikan) Penurunan Uang Muka
B21: (Kenaikan) Penurunan Persediaan | C21: ='Neraca (Balance Sheet)'!D15 | D21: Neraca - Selisih Persediaan | G21: =C21 | H21: • (Kenaikan) Penurunan Persediaan
B22: (Kenaikan) Penurunan Biaya Dibayar di Muka | C22: ='Neraca (Balance Sheet)'!D16 | D22: Neraca - Selisih Biaya Dibayar di Muka | G22: =C22 | H22: • (Kenaikan) Penurunan Biaya Dibayar di Muka
B23: (Kenaikan) Penurunan Persediaan Biologis | C23: ='Neraca (Balance Sheet)'!D17 | D23: Neraca - Selisih Persediaan Biologis | G23: =C23 | H23: • (Kenaikan) Penurunan Persediaan Biologis
B24: (Kenaikan) Penurunan Estimasi Klaim Pajak | C24: ='Neraca (Balance Sheet)'!D26 | D24: Neraca - Selisih Estimasi Klaim Pajak | G24: =C24 | H24: • (Kenaikan) Penurunan Estimasi Klaim Pajak
B25: Kenaikan (Penurunan) Utang Usaha | C25: =-'Neraca (Balance Sheet)'!D39 | D25: Neraca - ( - Selisih Utang Usaha ) | G25: =C25 | H25: • Kenaikan (Penurunan) Utang Usaha
B26: Kenaikan (Penurunan) Utang Pajak | C26: =-'Neraca (Balance Sheet)'!D40 | D26: Neraca - ( - Selisih Utang Pajak ) | G26: =C26 | H26: • Kenaikan (Penurunan) Utang Pajak
B27: Kenaikan (Penurunan) Uang Muka Penjualan | C27: =-'Neraca (Balance Sheet)'!D41 | D27: Neraca - ( - Selisih Uang Muka Penjualan ) | G27: =C27 | H27: • Kenaikan (Penurunan) Uang Muka Penjualan
B28: Kenaikan (Penurunan) Biaya Masih Harus Dibayar | C28: =-'Neraca (Balance Sheet)'!D42 | D28: Neraca - ( - Selisih Biaya Masih Harus Dibayar ) | G28: =C28 | H28: • Kenaikan (Penurunan) Biaya Masih Harus Dibayar
B29: Kenaikan (Penurunan) Imbalan Kerja Jangka Pendek | C29: =-'Neraca (Balance Sheet)'!D43 | D29: Neraca - ( - Selisih Imbalan Kerja Jangka Pendek ) | G29: =C29 | H29: • Kenaikan (Penurunan) Imbalan Kerja Jangka Pendek
B30: Kenaikan (Penurunan) Utang Lain-lain - Pihak Ketiga | C30: =-'Neraca (Balance Sheet)'!D44 | D30: Neraca - ( - Selisih Utang Lain-lain - Pihak Ketiga ) | G30: =C30 | H30: • Kenaikan (Penurunan) Utang Lain-lain - Pihak Ketiga
B31: Kenaikan (Penurunan) Utang Lain-lain - Pihak Berelasi | C31: =-'Neraca (Balance Sheet)'!D45 | D31: Neraca - ( - Selisih Utang Lain-lain - Pihak Berelasi ) | G31: =C31 | H31: • Kenaikan (Penurunan) Utang Lain-lain - Pihak Berelasi
B32: Kenaikan (Penurunan) Imbalan Kerja Karyawan Jangka Panjang | C32: =-'Neraca (Balance Sheet)'!D51 | D32: Neraca - ( - Selisih Imbalan Kerja Karyawan Jangka Panjang ) | G32: =C32 | H32: • Kenaikan (Penurunan) Imbalan Kerja Karyawan Jangka Panjang
B33: Kas Bersih Diperoleh dari Aktivitas Operasi | C33: =SUM(C8,C10,C11,C12,C13,C15,C16,C17,C18,C19,C20,C21,C22,C23,C24,C25,C26,C27,C28,C29,C30,C31,C32) | D33: Total Arus Kas Operasi | G33: ='Laba Rugi (Income Statement)'!B25 | H33: • Beban Pajak Penghasilan (Kini & Tangguhan)
G34: =C13 | H34: • (Kenaikan) Penurunan Aset Pajak Tangguhan
A35: B | B35: ARUS KAS DARI AKTIVITAS INVESTASI | G35: ='Laba Rugi (Income Statement)'!B16 | H35: • Penerimaan Pendapatan Bunga / Keuangan
B36: Perolehan Aset Tetap (Harga Perolehan) | C36: ='Neraca (Balance Sheet)'!D22 | D36: Neraca - Selisih Harga Perolehan Aset Tetap | G36: =SUM(G8,G10,G11,G12,G13,G15,G16,G17,G18,G19,G20,G21,G22,G23,G24,G25,G26,G27,G28,G29,G30,G31,G32,G33,G34,G35) | H36: Kas Bersih Diperoleh dari Aktivitas Operasi
B37: Uang Muka Pembelian Aset Tetap | C37: ='Neraca (Balance Sheet)'!D25 | D37: Neraca - Selisih Uang Muka Pembelian AT
B38: Penambahan Tanaman Belum Menghasilkan | C38: ='Neraca (Balance Sheet)'!D31 | D38: Neraca - Selisih TBM Bibit Durian | H38: 2. ARUS KAS DARI AKTIVITAS INVESTASI
B39: Penambahan HTI | C39: ='Neraca (Balance Sheet)'!D29 | D39: Neraca - Selisih HTI | G39: =C36 | H39: • Perolehan Aset Tetap (Harga Perolehan)
B40: Pembelian / Penambahan Aset Lainnya | C40: ='Neraca (Balance Sheet)'!D32 | D40: Neraca - Selisih Aset Lainnya | G40: =C37 | H40: • Uang Muka Pembelian Aset Tetap
B41: Piutang Pihak Berelasi (Jangka Panjang) | C41: ='Neraca (Balance Sheet)'!D27 | D41: Neraca - Selisih Piutang Pihak Berelasi | G41: =C38 | H41: • Penambahan Tanaman Belum Menghasilkan
B42: Penambahan Investasi (setelah eliminasi laba belum terealisasi) | C42: ='Neraca (Balance Sheet)'!D28-'Neraca (Balance Sheet)'!D60 | D42: Neraca - Selisih Investment - Selisih Laba belum terealisasi Colorpak (non-kas) | G42: =C39 | H42: • Penambahan HTI
B43: Kas Bersih Digunakan untuk Aktivitas Investasi | C43: =SUM(C36,C37,C38,C39,C40,C41,C42) | D43: Total Arus Kas Investasi | G43: =C40 | H43: • Pembelian / Penambahan Aset Lainnya
G44: =C41 | H44: • Piutang Pihak Berelasi (Jangka Panjang)
A45: C | B45: ARUS KAS DARI AKTIVITAS PENDANAAN | G45: =C42 | H45: • Penambahan Investasi (setelah eliminasi laba belum terealisasi)
B46: Kenaikan (Penurunan) Utang Bank Jangka Pendek | C46: =-'Neraca (Balance Sheet)'!D38 | D46: Neraca - ( - Selisih Utang Bank JP ) | G46: =SUM(G39,G40,G41,G42,G43,G44,G45) | H46: Kas Bersih Digunakan untuk Aktivitas Investasi
B47: Kenaikan (Penurunan) Utang Bank Jangka Panjang | C47: =-'Neraca (Balance Sheet)'!D52 | D47: Neraca - ( - Selisih Utang Bank Panjang )
B48: Kenaikan (Penurunan) Utang Pihak Berelasi Jangka Pendek | C48: =-'Neraca (Balance Sheet)'!D46 | D48: Neraca - ( - Selisih Utang Berelasi JP ) | H48: 3. ARUS KAS DARI AKTIVITAS PENDANAAN
B49: Pembayaran Utang Pihak Berelasi Jangka Panjang | C49: =-'Neraca (Balance Sheet)'!D53 | D49: Neraca - ( - Selisih Utang Berelasi Panjang ) | G49: =C46 | H49: • Kenaikan (Penurunan) Utang Bank Jangka Pendek
B50: Pembayaran Liabilitas Sewa | C50: =-('Neraca (Balance Sheet)'!D47+'Neraca (Balance Sheet)'!D54) | D50: Neraca - Total Selisih Liabilitas Sewa | G50: =C47 | H50: • Kenaikan (Penurunan) Utang Bank Jangka Panjang
B51: Setoran Modal / Tambahan Modal Disetor | C51: =-('Neraca (Balance Sheet)'!D59+'Neraca (Balance Sheet)'!D61) | D51: Neraca - ( - Selisih Modal & Tambahan Modal ) | G51: =C48 | H51: • Kenaikan (Penurunan) Utang Pihak Berelasi Jangka Pendek
B52: Kenaikan Akun Stress (Ekuitas Lainnya) | C52: =-'Neraca (Balance Sheet)'!D62 | D52: Neraca - ( - Selisih Stress ) | G52: =C49 | H52: • Pembayaran Utang Pihak Berelasi Jangka Panjang
B53: Penerimaan Setoran / Kenaikan NCI Net (di luar bagian laba NCI) | C53: =-'Neraca (Balance Sheet)'!D67-'Laba Rugi (Income Statement)'!B36-'Laba Rugi (Income Statement)'!B43 | D53: Neraca - Selisih NCI dikurangi NCI atas Laba & OCI | G53: =C50 | H53: • Pembayaran Liabilitas Sewa
B54: Kas Bersih Diperoleh dari Aktivitas Pendanaan | C54: =SUM(C46,C47,C48,C49,C50,C51,C52,C53) | D54: Total Arus Kas Pendanaan | G54: =C51 | H54: • Setoran Modal / Tambahan Modal Disetor
G55: =C52 | H55: • Kenaikan Akun Stress (Ekuitas Lainnya)
B56: KENAIKAN (PENURUNAN) BERSIH KAS DAN SETARA KAS | C56: =C33+C43+C54 | D56: Arus Kas (A + B + C) | G56: =C53 | H56: • Penerimaan Setoran / Kenaikan NCI Net (di luar bagian laba NCI)
B57: KAS DAN SETARA KAS AWAL PERIODE (31-DES-2023) | C57: ='Neraca (Balance Sheet)'!C8 | D57: Neraca - Kas & Setara Kas 2023 | G57: ='Laba Rugi (Income Statement)'!B17 | H57: • Pembayaran Beban Keuangan / Bunga
B58: KAS DAN SETARA KAS AKHIR PERIODE (31-DES-2024) | C58: =C56+C57 | D58: Kas Akhir (Sama dengan Neraca 2024) | G58: =SUM(G49,G50,G51,G52,G53,G54,G55,G56,G57) | H58: Kas Bersih Diperoleh dari Aktivitas Pendanaan
B59: VERIFIKASI / CEK SELISIH DENGAN NERACA 2024 | C59: =C58-'Neraca (Balance Sheet)'!B8 | D59: Harus 0 (Balance)
G60: =G36+G46+G58 | H60: KENAIKAN / (PENURUNAN) BERSIH KAS DAN SETARA KAS
G61: ='Neraca (Balance Sheet)'!C8 | H61: Kas dan Setara Kas Awal Tahun (31 Desember 2023)
G62: =G60+G61 | H62: Kas dan Setara Kas Akhir Tahun (31 Desember 2024)
G63: =G62-'Neraca (Balance Sheet)'!B8+(G62-C58) | H63: Cek: Selisih dengan Neraca 2024 & dengan Kertas Kerja (harus 0)
B66: Catatan:
B67: 1. Sumber data: Neraca & Laba Rugi 31-Des-2024 dari template.xlsx; 31-Des-2023 dari WS_Consol_PT_Bukit_Jaya_Semesta_2023.xlsx (sheet WBS WPL Consol, kolom CONSOLIDATED).
B68: 2. Kenaikan Investment mengandung laba belum terealisasi PT Colorpak Indonesia Tbk (non-kas) yang dieliminasi terhadap ekuitas; nilainya: | C68: =-'Neraca (Balance Sheet)'!D60
B69: 3. Penyesuaian saldo laba = Selisih Saldo Laba di Neraca dikurangi Laba Komprehensif Mayoritas di Laba Rugi (idealnya 0 / pembulatan).
B70: 4. Arus kas tahun 2023 tidak disusun karena file sumber tidak memuat Neraca 31-Des-2022 (kolom tahun pembanding bernilai 0).
B71: 5. File SalesByOrderStatus (order Sep-2026) tidak digunakan: periode & entitasnya di luar laporan konsolidasi 2024-2023.

Sheet Neraca (Balance Sheet)
A1: PT BUKIT JAYA SEMESTA
A2: LAPORAN POSISI KEUANGAN (NERACA)
A3: Per 31 Desember 2024 dan 2023
A5: Account / Pos Keuangan | B5: 31-Dec-24 | C5: 31-Dec-23 | D5: Selisih / Perubahan | E5: Referensi 2023 (WBS WPL Consol)
A6: ASET
A7: ASET LANCAR
A8: Kas kecil | B8: 49663124528 | C8: 24203301123 | D8: =C8-B8 | E8: Baris 40 Total Kas & Setara Kas
A9: Restricted Cash | B9: 0 | C9: 0 | D9: =C9-B9 | E9: Baris 42
A10: Piutang usaha - bersih | B10: 12963459099 | C10: 5078206703 | D10: =C10-B10 | E10: Baris 117 (Pihak ketiga 105 + berelasi 113)
A11: Piutang lain-lain - pihak ketiga | B11: 2088735497 | C11: 3433169417 | D11: =C11-B11 | E11: Baris 127
A12: Piutang lain-lain - pihak berelasi | B12: 13543645093 | C12: 8950000000 | D12: =C12-B12 | E12: Baris 134
A13: Pajak dibayar di muka | B13: 281571895 | C13: 257219804 | D13: =C13-B13 | E13: Baris 144
A14: Uang muka | B14: 327111435 | C14: 1383039636 | D14: =C14-B14 | E14: Baris 159
A15: Persediaaan | B15: 3825027103 | C15: 1434622080 | D15: =C15-B15 | E15: Baris 187
A16: Biaya dibayar dimuka | B16: 1171842931 | C16: 960221120 | D16: =C16-B16 | E16: Baris 151
A17: Persediaan bilogis | B17: 0 | C17: 0 | D17: =C17-B17 | E17: -
A18: TOTAL ASET LANCAR | B18: =SUM(B8:B17) | C18: =SUM(C8:C17) | D18: =C18-B18
A20: ASET TIDAK LANCAR
A21: Aset tetap
A22: Harga perolehan | B22: 604765019086 | C22: 537668235420 | D22: =C22-B22 | E22: Baris 275 (termasuk properti investasi)
A23: Penyusutan | B23: -38841748680 | C23: -39986601780 | D23: =C23-B23 | E23: Baris 296
A24: Net Book Value | B24: =SUM(B22:B23) | C24: =SUM(C22:C23) | D24: =C24-B24
A25: Uang Muka Pembelian Aset Tetap | B25: 0 | C25: 0 | D25: =C25-B25 | E25: Baris 302
A26: Estimasi klaim pajak | B26: 75307299 | C26: 0 | D26: =C26-B26 | E26: -
A27: Piutang pihak berelasi | B27: 0 | C27: 0 | D27: =C27-B27 | E27: Baris 308
A28: Investment | B28: 67404618000 | C28: 65528008185 | D28: =C28-B28 | E28: Baris 245
A29: HTI | B29: 0 | C29: 0 | D29: =C29-B29 | E29: -
A30: Aset pajak tangguhan | B30: 766214497 | C30: 1625452428 | D30: =C30-B30 | E30: Baris 341
A31: Tanaman Belum Menghasilkan - Bibit Durian | B31: 318750000 | C31: 318750000 | D31: =C31-B31 | E31: Baris 333
A32: Aset lainnya | B32: 427749144 | C32: 50000000 | D32: =C32-B32 | E32: Baris 346
A33: TOTAL ASET TIDAK LANCAR | B33: =B24+SUM(B25:B32) | C33: =C24+SUM(C25:C32) | D33: =C33-B33
A34: TOTAL ASET | B34: =B18+B33 | C34: =C18+C33 | D34: =C34-B34
A36: LIABILITAS
A37: LIABILITAS JANGKA PENDEK
A38: Utang bank | B38: 5850000000 | C38: 17500000000 | D38: =C38-B38 | E38: Baris 367
A39: Utang usaha | B39: 5017737008 | C39: 505654243 | D39: =C39-B39 | E39: Baris 411
A40: Utang Pajak | B40: 17506015406 | C40: 1114165636 | D40: =C40-B40 | E40: Baris 464
A41: Uang muka penjualan | B41: 0 | C41: 648000000 | D41: =C41-B41 | E41: Baris 469
A42: Biaya masih harus dibayar | B42: 1618002579 | C42: 2010524052 | D42: =C42-B42 | E42: Baris 449
A43: Imbalan kerja janga pendek | B43: 357242000 | C43: 0 | D43: =C43-B43 | E43: -
A44: Utang lain-lain - pihak ketiga | B44: 1293050662 | C44: 2179697795 | D44: =C44-B44 | E44: Baris 419
A45: Utang lain-lain - pihak berelasi | B45: 2279605092 | C45: 7644345919 | D45: =C45-B45 | E45: Baris 432
A46: Utang pihak berelasi - jangka pendek | B46: 0 | C46: 0 | D46: =C46-B46 | E46: Baris 476
A47: Liabilitas sewa | B47: 1106759005 | C47: 811931047 | D47: =C47-B47 | E47: Baris 474
A48: TOTAL LIABILITAS JANGKA PENDEK | B48: =SUM(B38:B47) | C48: =SUM(C38:C47) | D48: =C48-B48
A50: LIABILITAS JANGKA PANJANG
A51: Imbalan kerja karyawan | B51: 3901933524 | C51: 2899127504 | D51: =C51-B51 | E51: Baris 489
A52: Utang bank | B52: 70268000000 | C52: 52987000000 | D52: =C52-B52 | E52: Baris 486
A53: Utang pihak berelasi | B53: 106524999999 | C53: 185424812622 | D53: =C53-B53 | E53: Baris 531
A54: Liabilitas sewa | B54: 311982223 | C54: 121640061 | D54: =C54-B54 | E54: Baris 536
A55: TOTAL LIABILITAS JANGKA PANJANG | B55: =SUM(B51:B54) | C55: =SUM(C51:C54) | D55: =C55-B55
A56: TOTAL LIABILITAS | B56: =B48+B55 | C56: =C48+C55 | D56: =C56-B56
A58: EKUITAS
A59: Modal disetor | B59: 20000000000 | C59: 20000000000 | D59: =C59-B59 | E59: Baris 565
A60: Laba/ (Rugi) belum terealisasi - PT Colorpak Indonesia Tbk | B60: 11498752001 | C60: 9792104501 | D60: =C60-B60 | E60: Baris 573
A61: Tambahan modal di setor | B61: 8000000000 | C61: 8000000000 | D61: =C61-B61 | E61: Baris 546
A62: Stress | B62: 256473449 | C62: 0 | D62: =C62-B62 | E62: -
A63: Retained earning
A64: Beginning balance | B64: 192833795710 | C64: 187154813818 | D64: =C64-B64 | E64: Baris 576
A65: Current earning | B65: 115230255592 | C65: 5678981891 | D65: =C65-B65 | E65: Baris 592
A66: Ending balance | B66: =SUM(B64:B65) | C66: =SUM(C64:C65) | D66: =C66-B66
A67: NCI | B67: 154925822676 | C67: 106430825047 | D67: =C67-B67 | E67: Baris 550
A68: TOTAL EKUITAS | B68: =B59+B60+B61+B62+B66+B67 | C68: =C59+C60+C61+C62+C66+C67 | D68: =C68-B68
A69: TOTAL LIABILITAS DAN EKUITAS | B69: =B56+B68 | C69: =C56+C68 | D69: =C69-B69
A71: Cek: Total Liabilitas & Ekuitas - Total Aset (harus 0) | B71: =B69-B34 | C71: =C69-C34
A73: Sumber data:
A74: • 31-Dec-24: template.xlsx, sheet Neraca kolom 31-Dec-24.
A75: • 31-Dec-23: WS_Consol_PT_Bukit_Jaya_Semesta_2023.xlsx › 'WBS WPL Consol' kolom AH (CONSOLIDATED, Per Audit, 31-Des-2023).
A76: • Kolom "Selisih / Perubahan" = 2023 - 2024 (dipakai langsung oleh Kertas Kerja Cash Flow).

Sheet Laba Rugi (Income Statement)
A1: PT BUKIT JAYA SEMESTA
A2: LAPORAN LABA RUGI DAN PENDAPATAN KOMPREHENSIF LAIN
A3: Untuk Tahun yang Berakhir pada 31 Desember 2024 dan 2023
A5: Account / Pos Laba Rugi | B5: 31-Dec-24 | C5: 31-Dec-23 | D5: Selisih | E5: Referensi 2023 (WBS WPL Consol)
A6: Penjualan | B6: 92234715659 | C6: 64437082090 | D6: =C6-B6 | E6: Baris 636
A7: Beban Pokok Penjualan | B7: 36602877527 | C7: 17188336641 | D7: =C7-B7 | E7: Baris 701
A8: Total Laba Kotor | B8: =B6-B7 | C8: =C6-C7 | D8: =C8-B8
A10: Operating Expense:
A11: Beban Usaha | B11: 41184649120 | C11: 46412531236 | D11: =C11-B11 | E11: Baris 773
A12: Total Operating Expense | B12: =B11 | C12: =C11 | D12: =C12-B12
A13: Operating Income | B13: =B8-B12 | C13: =C8-C12 | D13: =C13-B13
A15: Other Income (Expense):
A16: Pendapatan Bunga | B16: 10165418608 | C16: 7264778074 | D16: =C16-B16 | E16: Baris 783 (pendapatan keuangan: bunga & dividen)
A17: Finance Expense | B17: -2443136567 | C17: -2116114767 | D17: =C17-B17 | E17: Baris 794
A18: Lain-lain Net | B18: 98866274584 | C18: 312115524 | D18: =C18-B18 | E18: Baris 821
A19: Total Other Income (Expense) | B19: =SUM(B16:B18) | C19: =SUM(C16:C18) | D19: =C19-B19
A20: Income Before Tax | B20: =B13+B19 | C20: =C13+C19 | D20: =C20-B20
A22: Taksiran Pajak Penghasilan:
A23: Tahun Berjalan | B23: -1696705500 | C23: -960889 | D23: =C23-B23 | E23: Baris 833
A24: Ditangguhkan | B24: -1949871786 | C24: -1384371756 | D24: =C24-B24 | E24: Baris 834
A25: Tax Expense | B25: =SUM(B23:B24) | C25: =SUM(C23:C24) | D25: =C25-B25
A26: Net Income (Laba Bersih) | B26: =B20+B25 | C26: =C20+C25 | D26: =C26-B26
A29: PENGHASILAN KOMPREHENSIF LAIN
A30: Selisih laba rugi aktuarial atas imbalan kerja | B30: -132361128 | C30: 72787959 | D30: =C30-B30 | E30: Baris 847
A31: Efek pajak terkait - imbalan kerja | B31: 29119448 | C31: 69583345 | D31: =C31-B31 | E31: Baris 848
A32: Total Penghasilan Komprehensif Lain | B32: =SUM(B30:B31) | C32: =SUM(C30:C31) | D32: =C32-B32
A34: TOTAL PENGHASILAN KOMPREHENSIF LAIN | B34: =B26+B32 | C34: =C26+C32 | D34: =C34-B34
A36: NONCONTROLLING INEREST (PL) | B36: 2.0695186e+09 | C36: -636305110 | D36: =C36-B36 | E36: Baris 854
A38: TOTAL NETO TAHUN BERJALAN - Mayoritas | B38: =B34-B36 | C38: =C34-C36 | D38: =C38-B38
A40: NONCONTROLLING INEREST (PL)
A41: OCI | B41: -17753208 | C41: 14557592 | D41: =C41-B41 | E41: Baris 859
A42: Pajak terkait | B42: 3905705.7 | C42: -3202670 | D42: =C42-B42 | E42: Baris 860
A43: Total NCI atas OCI | B43: =SUM(B41:B42) | C43: =SUM(C41:C42) | D43: =C43-B43
A45: LABA KOMPREHENSIF - Mayoritas (Current Earning) | B45: =B38-B43 | C45: =C38-C43 | D45: =C45-B45
A48: Selisih Laba Bersih vs Laba Komprehensif Mayoritas | B48: =B26-B45 | C48: =C26-C45 | D48: =C48-B48
A50: Cek ke Neraca: Current Earning (Neraca) - Laba Komprehensif Mayoritas | B50: ='Neraca (Balance Sheet)'!B65-B45 | C50: ='Neraca (Balance Sheet)'!C65-C45
A52: Sumber data: 2024 dari template.xlsx (kolom 31-Dec-24); 2023 dari WS_Consol_PT_Bukit_Jaya_Semesta_2023.xlsx › 'WBS WPL Consol' kolom AH (CONSOLIDATED, Per Audit, 31-Des-2023).
